odoo/addons/easy_search_task_ticket/README.rst
odoo/addons/easy_search_task_ticket/__init__.py
odoo/addons/easy_search_task_ticket/__manifest__.py
odoo/addons/easy_search_task_ticket/i18n/es.po
odoo/addons/easy_search_task_ticket/static/description/icon.png
odoo/addons/easy_search_task_ticket/static/src/js/quick_task_ticket_navigation.js
odoo/addons/easy_search_task_ticket/static/src/scss/quick_task_ticket_navigation.scss
odoo/addons/easy_search_task_ticket/static/src/xml/quick_task_ticket_navigation.xml
odoo/addons/easy_search_task_ticket/views/assets.xml
odoo12_addon_easy_search_task_ticket-12.0.1.0.0.dist-info/METADATA
odoo12_addon_easy_search_task_ticket-12.0.1.0.0.dist-info/WHEEL
odoo12_addon_easy_search_task_ticket-12.0.1.0.0.dist-info/top_level.txt
odoo12_addon_easy_search_task_ticket-12.0.1.0.0.dist-info/RECORD
